b/__main__.py
b/bugs.py
b/command.py
b/config.py
b/context.py
b/exceptions.py
b/migrations.py
b/schema/bug.schema.json
b/settings.py
b/templates/bug.bug.yaml
b/templates/chore.bug.yaml
b/templates/feature.bug.yaml
b/templates.py
b/utils.py
b_bugtracker-3.3.0.dist-info/entry_points.txt
b_bugtracker-3.3.0.dist-info/licenses/LICENSE
b_bugtracker-3.3.0.dist-info/METADATA
b_bugtracker-3.3.0.dist-info/WHEEL
b_bugtracker-3.3.0.dist-info/RECORD
