Metadata-Version: 2.4
Name: b-bugtracker
Version: 3.3.0
Summary: A simple, distributed bug tracker.
License: GPL-3.0-or-later
License-File: LICENSE
Author: Michael Diamond
Author-email: michael@digitalgemstones.com
Requires-Python: >=3.10,<4.0
Classifier: License :: OSI Approved :: GNU General Public License v3 or later (GPLv3+)
Classifier: Programming Language :: Python :: 3
Classifier: Programming Language :: Python :: 3.10
Classifier: Programming Language :: Python :: 3.11
Classifier: Programming Language :: Python :: 3.12
Classifier: Programming Language :: Python :: 3.13
Classifier: Programming Language :: Python :: 3.14
Requires-Dist: PyYAML (>=6.0,<7.0)
Requires-Dist: appdirs (>=1.4.4,<2.0.0)
Requires-Dist: click (>=8.1.7,<9.0.0)
Requires-Dist: jsonschema (>=4.17.3,<5.0.0)
Requires-Dist: rich (>=13.3.5,<14.0.0)
Requires-Dist: rich-click (>=1.9.4,<2.0.0)
Project-URL: Homepage, https://jwjulien.github.io/b
Project-URL: Repository, https://github.com/jwjulien/b
